hypergumbo_core/__init__.py
hypergumbo_core/__main__.py
hypergumbo_core/_embedding_data.py
hypergumbo_core/build_grammars.py
hypergumbo_core/catalog.py
hypergumbo_core/cli.py
hypergumbo_core/compact.py
hypergumbo_core/datamodels.py
hypergumbo_core/discovery.py
hypergumbo_core/entrypoints.py
hypergumbo_core/framework_patterns.py
hypergumbo_core/ir.py
hypergumbo_core/limits.py
hypergumbo_core/metrics.py
hypergumbo_core/paths.py
hypergumbo_core/profile.py
hypergumbo_core/ranking.py
hypergumbo_core/schema.py
hypergumbo_core/sketch.py
hypergumbo_core/sketch_embeddings.py
hypergumbo_core/slice.py
hypergumbo_core/supply_chain.py
hypergumbo_core/symbol_resolution.py
hypergumbo_core/taxonomy.py
hypergumbo_core/user_config.py
hypergumbo_core/analyze/__init__.py
hypergumbo_core/analyze/all_analyzers.py
hypergumbo_core/analyze/base.py
hypergumbo_core/analyze/registry.py
hypergumbo_core/frameworks/adonisjs.yaml
hypergumbo_core/frameworks/aiohttp.yaml
hypergumbo_core/frameworks/akka-http.yaml
hypergumbo_core/frameworks/android.yaml
hypergumbo_core/frameworks/aspnet.yaml
hypergumbo_core/frameworks/bottle.yaml
hypergumbo_core/frameworks/cakephp.yaml
hypergumbo_core/frameworks/celery.yaml
hypergumbo_core/frameworks/cli-go.yaml
hypergumbo_core/frameworks/cli-js.yaml
hypergumbo_core/frameworks/cli-ruby.yaml
hypergumbo_core/frameworks/cli-rust.yaml
hypergumbo_core/frameworks/cli.yaml
hypergumbo_core/frameworks/codeigniter.yaml
hypergumbo_core/frameworks/config-conventions.yaml
hypergumbo_core/frameworks/django.yaml
hypergumbo_core/frameworks/electron.yaml
hypergumbo_core/frameworks/express.yaml
hypergumbo_core/frameworks/falcon.yaml
hypergumbo_core/frameworks/fastapi.yaml
hypergumbo_core/frameworks/fastify.yaml
hypergumbo_core/frameworks/feathers.yaml
hypergumbo_core/frameworks/flask-appbuilder.yaml
hypergumbo_core/frameworks/flask.yaml
hypergumbo_core/frameworks/fuelphp.yaml
hypergumbo_core/frameworks/go-web.yaml
hypergumbo_core/frameworks/grape.yaml
hypergumbo_core-2.0.0.dist-info/METADATA
hypergumbo_core-2.0.0.dist-info/WHEEL
hypergumbo_core-2.0.0.dist-info/entry_points.txt
hypergumbo_core-2.0.0.dist-info/RECORD
